README.md
setup.py
stocker_d/__init__.py
stocker_d/stocker.py
stocker_d/stocker_d.py
stocker_d.egg-info/PKG-INFO
stocker_d.egg-info/SOURCES.txt
stocker_d.egg-info/dependency_links.txt
stocker_d.egg-info/requires.txt
stocker_d.egg-info/top_level.txt