Metadata-Version: 2.1
Name: stocker-d
Version: 0.1rc0
Summary: Stocker D
Home-page: UNKNOWN
Author-email: david.woodruff@coxautoinc.com
License: UNKNOWN
Keywords: stocker
Platform: UNKNOWN
Classifier: Intended Audience :: Developers
Classifier: Natural Language :: English
Classifier: Programming Language :: Python
Classifier: Programming Language :: Python :: 3.7
